kleides_dssoclient/__init__.py
kleides_dssoclient/backends.py
kleides_dssoclient/dssoclient.py
kleides_dssoclient/middleware.py
kleides_dssoclient-0.9.data/data/share/doc/kleides_dssoclient/CHANGES.rst
kleides_dssoclient-0.9.data/data/share/doc/kleides_dssoclient/LICENSE
kleides_dssoclient-0.9.data/data/share/doc/kleides_dssoclient/README.rst
kleides_dssoclient-0.9.dist-info/LICENSE
kleides_dssoclient-0.9.dist-info/METADATA
kleides_dssoclient-0.9.dist-info/WHEEL
kleides_dssoclient-0.9.dist-info/top_level.txt
kleides_dssoclient-0.9.dist-info/RECORD
