Metadata-Version: 2.1
Name: kleides_dssoclient
Version: 0.9
Summary: Kleides Discourse SSO client for Django
Home-page: https://github.com/ossobv/kleides-dssoclient
Author: Walter Doekes, OSSO B.V.
Author-email: wjdoekes+kleides@osso.nl
License: GPLv3+
Platform: linux
Classifier: Development Status :: 4 - Beta
Classifier: Environment :: Web Environment
Classifier: Framework :: Django
Classifier: Framework :: Django :: 2.2
Classifier: Framework :: Django :: 3.0
Classifier: Framework :: Django :: 3.1
Classifier: Intended Audience :: System Administrators
Classifier: License :: OSI Approved :: GNU General Public License v3 or later (GPLv3+)
Classifier: Operating System :: POSIX :: Linux
Classifier: Programming Language :: Python
Classifier: Programming Language :: Python :: 3.6
Classifier: Programming Language :: Python :: 3.7
Classifier: Programming Language :: Python :: 3.8
Classifier: Topic :: System :: Systems Administration :: Authentication/Directory
License-File: LICENSE
